crestic.py
crestic-1.1.0.dist-info/licenses/LICENSE
crestic-1.1.0.dist-info/METADATA
crestic-1.1.0.dist-info/WHEEL
crestic-1.1.0.dist-info/entry_points.txt
crestic-1.1.0.dist-info/top_level.txt
crestic-1.1.0.dist-info/RECORD
