Metadata-Version: 2.4
Name: crestic
Version: 1.1.0
Summary: Configurable restic
Author-email: Nils Werner <nils.werner@gmail.com>
License-Expression: MIT
Project-URL: Homepage, https://github.com/nils-werner/crestic/
Project-URL: CI, https://app.circleci.com/pipelines/github/nils-werner/crestic
Classifier: Intended Audience :: Developers
Classifier: Intended Audience :: System Administrators
Classifier: Intended Audience :: End Users/Desktop
Classifier: Natural Language :: English
Classifier: Operating System :: MacOS :: MacOS X
Classifier: Operating System :: POSIX
Classifier: Operating System :: POSIX :: BSD
Classifier: Operating System :: POSIX :: Linux
Classifier: Programming Language :: Python
Classifier: Programming Language :: Python :: 3
Classifier: Programming Language :: Python :: 3 :: Only
Classifier: Programming Language :: Python :: 3.6
Classifier: Programming Language :: Python :: 3.7
Classifier: Programming Language :: Python :: 3.8
Classifier: Programming Language :: Python :: Implementation :: CPython
Classifier: Topic :: System :: Archiving :: Backup
Requires-Python: >=3.6
License-File: LICENSE
Dynamic: license-file
